{
  "users": [
    {
      "id": 1,
      "fullName": "Melissa Wallis",
      "email": "melissa@email.com",
      "isStaff": true
    },
    {
      "email": "customer@email.com",
      "fullName": "Jane Doe",
      "isStaff": false,
      "id": 2
    },
    {
      "email": "",
      "fullName": "",
      "isStaff": false,
      "": "customer@email.com",
      "id": 3
    }
  ],
  "itemTypes": [
    {
      "id": 1,
      "type": "Cross Stitch"
    },
    {
      "id": 2,
      "type": "Embroidery"
    },
    {
      "id": 3,
      "type": "Miniature"
    },
    {
      "id": 4,
      "type": "Wall Hanging"
    }
  ],
  "items": [
    {
      "name": "Roses",
      "description": "9\" Roses embroidery",
      "price": "100",
      "image": "http://res.cloudinary.com/dkst6uh8j/image/upload/v1670958341/h2dzlabbap4xncjicxf0.png",
      "itemTypeId": 2,
      "id": 36
    },
    {
      "name": "Spooky Kitty",
      "description": "8\" Halloween cat embroidery",
      "price": "50",
      "image": "http://res.cloudinary.com/dkst6uh8j/image/upload/v1670961746/xcsljgvtxrl14lxyiclm.png",
      "itemTypeId": 2,
      "id": 38
    },
    {
      "name": "Little Library",
      "description": "Library miniature",
      "price": "75",
      "image": "http://res.cloudinary.com/dkst6uh8j/image/upload/v1670966952/irgha2ssfnxwiqjhx0zx.png",
      "itemTypeId": 3,
      "id": 41
    },
    {
      "name": "Mini Bouquet",
      "description": "5\" Floral bouquet embroidery",
      "price": "35",
      "image": "http://res.cloudinary.com/dkst6uh8j/image/upload/v1670972368/lp568fbu1ynqr579qbxj.png",
      "itemTypeId": 2,
      "id": 43
    },
    {
      "name": "Small Roses",
      "description": "3\" Roses cross stitch",
      "price": "30",
      "image": "http://res.cloudinary.com/dkst6uh8j/image/upload/v1670981786/smkbfoeiqtetl15hr9oi.png",
      "itemTypeId": 1,
      "id": 48
    },
    {
      "name": "Crafter's Manifesto",
      "description": "10\" Pursuit of Craftiness cross stitch",
      "price": "50",
      "image": "http://res.cloudinary.com/dkst6uh8j/image/upload/v1671052115/ykjp21xcggemfn9hxlct.png",
      "itemTypeId": 1,
      "id": 50
    },
    {
      "name": "SSDGM",
      "description": "7\" My Favorite Murder embroidery",
      "price": "100",
      "image": "http://res.cloudinary.com/dkst6uh8j/image/upload/v1672606891/rr6g4ucdyqdp9jcn54wt.png",
      "itemTypeId": 2,
      "id": 51
    },
    {
      "name": "Wall Hanging",
      "description": "Woven wall hanging",
      "price": "150",
      "image": "http://res.cloudinary.com/dkst6uh8j/image/upload/v1672606940/qx8gszskpgwgwyiktbdx.png",
      "itemTypeId": 4,
      "id": 52
    },
    {
      "name": "Wil's Greenhouse",
      "description": "Greenhouse miniature",
      "price": "75",
      "image": "http://res.cloudinary.com/dkst6uh8j/image/upload/v1672606991/ugwj6701huohsfhx2kfy.png",
      "itemTypeId": 3,
      "id": 53
    },
    {
      "name": "Robin",
      "description": "8\" Bird embroidery",
      "price": "45",
      "image": "http://res.cloudinary.com/dkst6uh8j/image/upload/v1672607038/awno4nrm9crns6nj3ilo.png",
      "itemTypeId": 2,
      "id": 54
    },
    {
      "name": "Nashville",
      "description": "8\" Nashville skyline cross stitch",
      "price": "40",
      "image": "http://res.cloudinary.com/dkst6uh8j/image/upload/v1672607092/dkucywj0y4nilkmdwren.png",
      "itemTypeId": 1,
      "id": 55
    },
    {
      "name": "Blue Bird",
      "description": "8\" Bird cross stitch",
      "price": "40",
      "image": "http://res.cloudinary.com/dkst6uh8j/image/upload/v1672607144/oy1uq7upjyrbazaneqvm.png",
      "itemTypeId": 1,
      "id": 56
    },
    {
      "name": "Blue Bargello",
      "description": "Blue bargello wall hanging",
      "price": "45",
      "image": "http://res.cloudinary.com/dkst6uh8j/image/upload/v1672607190/ofq6ry8jl0fhj9t91x2c.png",
      "itemTypeId": 4,
      "id": 57
    },
    {
      "name": "Totoro's Hut",
      "description": "Totoro house and garden miniature",
      "price": "40",
      "image": "http://res.cloudinary.com/dkst6uh8j/image/upload/v1672607226/ta1nxta4h0kp60xp7pnu.png",
      "itemTypeId": 3,
      "id": 58
    },
    {
      "name": "Bambi's Dad",
      "description": "10\" Deer in the winter woods embroidery",
      "price": "60",
      "image": "http://res.cloudinary.com/dkst6uh8j/image/upload/v1672607269/t5lqaaaittv6pw3fvzbh.png",
      "itemTypeId": 2,
      "id": 59
    },
    {
      "name": "Teensy Teahouse",
      "description": "Teahouse miniature",
      "price": "75",
      "image": "http://res.cloudinary.com/dkst6uh8j/image/upload/v1672607307/obht7x6m8ruvh00fbamw.png",
      "itemTypeId": 3,
      "id": 60
    },
    {
      "name": "Pink Bargello",
      "description": "Pink bargello wall hanging",
      "price": "50",
      "image": "http://res.cloudinary.com/dkst6uh8j/image/upload/v1672607345/tf6phhbxoou5uw6iicv3.png",
      "itemTypeId": 4,
      "id": 61
    },
    {
      "name": "Derpy Kitty",
      "description": "Framed cat cross stitch",
      "price": "50",
      "image": "http://res.cloudinary.com/dkst6uh8j/image/upload/v1672607378/ej213wuqhpzuxlyfewzz.png",
      "itemTypeId": 1,
      "id": 62
    }
  ]
}